dev/__init__.py
dev/boot.py
django_devapp-0.4.0.dist-info/METADATA
django_devapp-0.4.0.dist-info/WHEEL
django_devapp-0.4.0.dist-info/entry_points.txt
django_devapp-0.4.0.dist-info/licenses/LICENSE
django_devapp-0.4.0.dist-info/RECORD
