Metadata-Version: 2.4
Name: django-devapp
Version: 0.4.0
Summary: Basic tools to manage a django application outside of a Django project
License: BSD-3-Clause License
License-File: LICENSE
Author: George Tantiras
Requires-Python: >=3.11
Classifier: Development Status :: 3 - Alpha
Classifier: Environment :: Web Environment
Classifier: Framework :: Django
Classifier: Intended Audience :: Developers
Classifier: License :: Other/Proprietary License
Classifier: Programming Language :: Python :: 3
Classifier: Programming Language :: Python :: 3.11
Classifier: Programming Language :: Python :: 3.12
Classifier: Programming Language :: Python :: 3.13
Classifier: Programming Language :: Python :: 3.14
Classifier: Topic :: Internet :: WWW/HTTP
Requires-Dist: black (>=25.1.0,<26.0.0)
Requires-Dist: build (>=1.2.2.post1,<2.0.0)
Requires-Dist: click (>=8.1.8,<9.0.0)
Requires-Dist: django (>=5.1.6,<6.0.0)
Requires-Dist: ipython (>=9.0.0,<10.0.0)
Requires-Dist: twine (>=6.1.0,<7.0.0)
